<?xml version="1.0" encoding="utf-8"?>
<resources xmlns:tools="http://schemas.android.com/tools" tools:ignore="MissingTranslation">
    <bool name="current_gtfs_rts_schedule_available">true</bool>
    <bool name="current_gtfs_rts_frequency_available">false</bool>
    <string name="current_gtfs_rts_area_min_lat">46.734726</string>
    <string name="current_gtfs_rts_area_max_lat">46.938477</string>
    <string name="current_gtfs_rts_area_min_lng">-71.472099</string>
    <string name="current_gtfs_rts_area_max_lng">-71.149269</string>
    <integer name="current_gtfs_rts_first_departure_in_sec">1724058300</integer><!-- 2024/08/19 05:05:00 EDT -->
    <integer name="current_gtfs_rts_last_departure_in_sec">1725091560</integer><!-- 2024/08/31 04:06:00 EDT -->
</resources>
